pennylane_qulacs/__init__.py
pennylane_qulacs/_version.py
pennylane_qulacs/qulacs_device.py
pennylane_qulacs-0.43.0.dist-info/licenses/LICENSE
pennylane_qulacs-0.43.0.dist-info/METADATA
pennylane_qulacs-0.43.0.dist-info/WHEEL
pennylane_qulacs-0.43.0.dist-info/entry_points.txt
pennylane_qulacs-0.43.0.dist-info/top_level.txt
pennylane_qulacs-0.43.0.dist-info/RECORD
