Metadata-Version: 2.4
Name: pennylane-qulacs
Version: 0.43.0
Summary: PennyLane plugin for Qulacs.
Home-page: http://xanadu.ai
Maintainer: Xanadu Inc.
Maintainer-email: software@xanadu.ai
License: Apache License 2.0
Classifier: Development Status :: 4 - Beta
Classifier: Environment :: Console
Classifier: Intended Audience :: Science/Research
Classifier: License :: OSI Approved :: Apache Software License
Classifier: Natural Language :: English
Classifier: Operating System :: POSIX
Classifier: Operating System :: MacOS :: MacOS X
Classifier: Operating System :: POSIX :: Linux
Classifier: Operating System :: Microsoft :: Windows
Classifier: Programming Language :: Python
Classifier: Programming Language :: Python :: 3
Classifier: Programming Language :: Python :: 3.11
Classifier: Programming Language :: Python :: 3.12
Classifier: Programming Language :: Python :: 3.13
Classifier: Programming Language :: Python :: 3 :: Only
Classifier: Topic :: Scientific/Engineering :: Physics
Provides: pennylane_qulacs
License-File: LICENSE
Requires-Dist: pennylane>=0.43
Requires-Dist: numpy
Requires-Dist: scipy
Provides-Extra: cpu
Requires-Dist: qulacs>=0.1.10.1; extra == "cpu"
Provides-Extra: gpu
Requires-Dist: qulacs-gpu>=0.1.10.1; extra == "gpu"
Dynamic: classifier
Dynamic: description
Dynamic: description-content-type
Dynamic: home-page
Dynamic: license
Dynamic: license-file
Dynamic: maintainer
Dynamic: maintainer-email
Dynamic: provides
Dynamic: provides-extra
Dynamic: requires-dist
Dynamic: summary
